fds/__init__.py
fds/sdk/__init__.py
fds/sdk/FactSetProgrammaticEnvironment/__init__.py
fds/sdk/FactSetProgrammaticEnvironment/api_client.py
fds/sdk/FactSetProgrammaticEnvironment/configuration.py
fds/sdk/FactSetProgrammaticEnvironment/exceptions.py
fds/sdk/FactSetProgrammaticEnvironment/model_utils.py
fds/sdk/FactSetProgrammaticEnvironment/rest.py
fds/sdk/FactSetProgrammaticEnvironment/api/__init__.py
fds/sdk/FactSetProgrammaticEnvironment/api/calculations_api.py
fds/sdk/FactSetProgrammaticEnvironment/api/files_api.py
fds/sdk/FactSetProgrammaticEnvironment/apis/__init__.py
fds/sdk/FactSetProgrammaticEnvironment/model/__init__.py
fds/sdk/FactSetProgrammaticEnvironment/model/calculation.py
fds/sdk/FactSetProgrammaticEnvironment/model/calculation_status.py
fds/sdk/FactSetProgrammaticEnvironment/model/file_upload_status.py
fds/sdk/FactSetProgrammaticEnvironment/models/__init__.py
fds.sdk.FactSetProgrammaticEnvironment-0.22.1.dist-info/LICENSE
fds.sdk.FactSetProgrammaticEnvironment-0.22.1.dist-info/METADATA
fds.sdk.FactSetProgrammaticEnvironment-0.22.1.dist-info/WHEEL
fds.sdk.FactSetProgrammaticEnvironment-0.22.1.dist-info/top_level.txt
fds.sdk.FactSetProgrammaticEnvironment-0.22.1.dist-info/RECORD
